{
    "modified": 1716999178,
    "key": "group_619cdc7817eeb",
    "title": "Bloc posts list",
    "fields": [
        {
            "key": "field_61a0ca3778ce8",
            "label": "Liste",
            "name": "",
            "aria-label": "",
            "type": "accordion",
            "instructions": "",
            "required": 0,
            "conditional_logic": 0,
            "wrapper": {
                "width": "",
                "class": "",
                "id": ""
            },
            "open": 0,
            "multi_expand": 0,
            "endpoint": 0
        },
        {
            "key": "field_619cdcf0c5bdb",
            "label": "Type de contenu",
            "name": "post_type",
            "aria-label": "",
            "type": "select",
            "instructions": "",
            "required": 1,
            "conditional_logic": 0,
            "wrapper": {
                "width": "",
                "class": "",
                "id": ""
            },
            "choices": {
                "post": "Articles",
                "carte-carburant": "Cartes carburant"
            },
            "default_value": false,
            "allow_null": 0,
            "multiple": 0,
            "ui": 0,
            "return_format": "value",
            "ajax": 0,
            "placeholder": ""
        },
        {
            "key": "field_61a0ca8578cea",
            "label": "Nombre d'items",
            "name": "posts_per_page",
            "aria-label": "",
            "type": "number",
            "instructions": "Mettre 0 pour tout afficher.\r\nAttention au temps de chargements si il y a beaucoup d'éléments",
            "required": 0,
            "conditional_logic": 0,
            "wrapper": {
                "width": "",
                "class": "",
                "id": ""
            },
            "default_value": 3,
            "placeholder": "",
            "prepend": "",
            "append": "",
            "min": "",
            "max": "",
            "step": ""
        },
        {
            "key": "field_619ce46ae6f68",
            "label": "Item par ligne",
            "name": "columns",
            "aria-label": "",
            "type": "range",
            "instructions": "",
            "required": 0,
            "conditional_logic": 0,
            "wrapper": {
                "width": "",
                "class": "",
                "id": ""
            },
            "default_value": 3,
            "min": 1,
            "max": 6,
            "step": "",
            "prepend": "",
            "append": ""
        },
        {
            "key": "field_61a60b6d25bad",
            "label": "Pagination",
            "name": "",
            "aria-label": "",
            "type": "accordion",
            "instructions": "",
            "required": 0,
            "conditional_logic": 0,
            "wrapper": {
                "width": "",
                "class": "",
                "id": ""
            },
            "open": 0,
            "multi_expand": 0,
            "endpoint": 0
        },
        {
            "key": "field_61a890054d37c",
            "label": "Afficher la pagination",
            "name": "pagination_is_active",
            "aria-label": "",
            "type": "true_false",
            "instructions": "La pagination ne doit être activée que pour une seule liste de la page",
            "required": 1,
            "conditional_logic": 0,
            "wrapper": {
                "width": "",
                "class": "",
                "id": ""
            },
            "message": "",
            "default_value": 0,
            "ui": 1,
            "ui_on_text": "",
            "ui_off_text": ""
        },
        {
            "key": "field_61a60b2fab20d",
            "label": "Afficher un bouton \"Voir plus\"",
            "name": "see_more_is_active",
            "aria-label": "",
            "type": "true_false",
            "instructions": "Cette option masquera la pagination classique",
            "required": 1,
            "conditional_logic": 0,
            "wrapper": {
                "width": "",
                "class": "",
                "id": ""
            },
            "message": "",
            "default_value": 0,
            "ui": 1,
            "ui_on_text": "",
            "ui_off_text": ""
        },
        {
            "key": "field_61a60d44ab29e",
            "label": "Clone de Element bouton",
            "name": "see_more_button",
            "aria-label": "",
            "type": "clone",
            "instructions": "",
            "required": 0,
            "conditional_logic": [
                [
                    {
                        "field": "field_61a60b2fab20d",
                        "operator": "==",
                        "value": "1"
                    }
                ]
            ],
            "wrapper": {
                "width": "",
                "class": "",
                "id": ""
            },
            "clone": [
                "group_61a60c311770a"
            ],
            "display": "group",
            "layout": "row",
            "prefix_label": 0,
            "prefix_name": 0
        }
    ],
    "location": [
        [
            {
                "param": "block",
                "operator": "==",
                "value": "daeris\/post-list"
            }
        ]
    ],
    "menu_order": 0,
    "position": "normal",
    "style": "default",
    "label_placement": "top",
    "instruction_placement": "label",
    "hide_on_screen": "",
    "active": true,
    "description": "",
    "show_in_rest": 0
}
